gevopy/VERSION
gevopy/__init__.py
gevopy/algorithms.py
gevopy/database.py
gevopy/experiments.py
gevopy/fitness.py
gevopy/genetics.py
gevopy/random.py
gevopy/utils.py
gevopy/config/__init__.py
gevopy/config/defaults.toml
gevopy/tools/__init__.py
gevopy/tools/crossover.py
gevopy/tools/mutation.py
gevopy/tools/selection.py
gevopy-1.1.1.dist-info/LICENSE
gevopy-1.1.1.dist-info/METADATA
gevopy-1.1.1.dist-info/WHEEL
gevopy-1.1.1.dist-info/top_level.txt
gevopy-1.1.1.dist-info/RECORD
