Metadata-Version: 2.1
Name: gevopy
Version: 1.1.1
Summary: Genetics for Evolutionary Algorithms in Python.
License: GNU General Public License v3 (GPLv3)
Project-URL: Homepage, https://github.com/BorjaEst/gevopy/
Project-URL: Bug Tracker, https://github.com/BorjaEst/gevopy/issues
Classifier: Programming Language :: Python :: 3
Classifier: License :: OSI Approved :: GNU General Public License v3 (GPLv3)
Classifier: Operating System :: OS Independent
Requires-Python: >=3.10
License-File: LICENSE
Requires-Dist: numpy (~=1.23.4)
Requires-Dist: pydantic (~=1.10.2)
Requires-Dist: sortedcontainers (~=2.4.0)
Requires-Dist: dask[distributed] (~=2022.11.1)
Requires-Dist: neo4j (~=5.2.1)
